contique/__about__.py
contique/__init__.py
contique/helpers.py
contique/jacobian.py
contique/newton.py
contique/newtonxt.py
contique/numcont.py
contique/printinfo.py
contique-1.1.1.dist-info/licenses/LICENSE
contique-1.1.1.dist-info/METADATA
contique-1.1.1.dist-info/WHEEL
contique-1.1.1.dist-info/top_level.txt
contique-1.1.1.dist-info/RECORD
