Metadata-Version: 2.4
Name: contique
Version: 1.1.1
Summary: Numerical continuation of nonlinear equilibrium equations.
Author-email: Andreas Dutzler <a.dutzler@gmail.com>
License-Expression: GPL-3.0-or-later
Project-URL: Homepage, https://github.com/adtzlr/contique
Project-URL: Documentation, https://github.com/adtzlr/contique
Project-URL: Repository, https://github.com/adtzlr/contique
Project-URL: Issues, https://github.com/adtzlr/contique/issues
Project-URL: Changelog, https://github.com/adtzlr/contique/blob/main/CHANGELOG.md
Keywords: python,numeric-continuation,scientific-computing
Classifier: Development Status :: 5 - Production/Stable
Classifier: Programming Language :: Python
Classifier: Intended Audience :: Science/Research
Classifier: Operating System :: OS Independent
Classifier: Programming Language :: Python
Classifier: Programming Language :: Python :: 3
Classifier: Programming Language :: Python :: 3.10
Classifier: Programming Language :: Python :: 3.11
Classifier: Programming Language :: Python :: 3.12
Classifier: Programming Language :: Python :: 3.13
Classifier: Programming Language :: Python :: 3.14
Classifier: Topic :: Scientific/Engineering
Classifier: Topic :: Scientific/Engineering :: Mathematics
Classifier: Topic :: Utilities
Requires-Python: >=3.9
License-File: LICENSE
Requires-Dist: numpy
Requires-Dist: scipy
Dynamic: license-file
